{
  "generatedAt": "2026-03-06",
  "threads": [
    {
      "threadId": "thread:coherence-lattice-001",
      "status": "admitted-thread",
      "sourceAuditStatus": "admit",
      "targetPublisherAction": "annotate",
      "sourceInputIds": [
        "sonya:text:atlas-note-001",
        "sonya:text:atlas-note-002"
      ],
      "linkedConceptIds": [
        "concept:coherence-lattice",
        "concept:formal-coherence"
      ],
      "recursivePotentialScore": 0.74,
      "coherenceScore": 0.83,
      "riskScore": 0.14,
      "surfacedAt": "2026-03-06"
    }
  ]
}
